{"grid_search": [{"Number of components": 1, "Type of covariance": "diag", "BIC score": 48.966308469157916}, {"Number of components": 2, "Type of covariance": "diag", "BIC score": 59.19874978390469}, {"Number of components": 3, "Type of covariance": "diag", "BIC score": 70.37649121903732}, {"Number of components": 4, "Type of covariance": "diag", "BIC score": 86.47281106440332}, {"Number of components": 5, "Type of covariance": "diag", "BIC score": 95.53717061907646}, {"Number of components": 6, "Type of covariance": "diag", "BIC score": 114.99611987428705}, {"Number of components": 7, "Type of covariance": "diag", "BIC score": 120.23777672761341}, {"Number of components": 9, "Type of covariance": "diag", "BIC score": 156.38179593757144}, {"Number of components": 10, "Type of covariance": "diag", "BIC score": 164.92223933209212}, {"Number of components": 8, "Type of covariance": "diag", "BIC score": 181.17193735812987}], "n_cdrs": 76}