{"grid_search": [{"Number of components": 1, "Type of covariance": "diag", "BIC score": 52.19429573641626}, {"Number of components": 2, "Type of covariance": "diag", "BIC score": 61.405033201384484}, {"Number of components": 3, "Type of covariance": "diag", "BIC score": 71.19887758682553}, {"Number of components": 4, "Type of covariance": "diag", "BIC score": 80.28614144709258}, {"Number of components": 5, "Type of covariance": "diag", "BIC score": 87.97623442147979}, {"Number of components": 6, "Type of covariance": "diag", "BIC score": 108.75554002946619}, {"Number of components": 7, "Type of covariance": "diag", "BIC score": 114.93554440256428}, {"Number of components": 8, "Type of covariance": "diag", "BIC score": 158.07935289166008}, {"Number of components": 9, "Type of covariance": "diag", "BIC score": 165.2008766993277}, {"Number of components": 10, "Type of covariance": "diag", "BIC score": 178.4020544908234}], "n_cdrs": 76}