{"grid_search": [{"Number of components": 1, "Type of covariance": "diag", "BIC score": 92.11486917875445}, {"Number of components": 2, "Type of covariance": "diag", "BIC score": 100.30748850800094}, {"Number of components": 3, "Type of covariance": "diag", "BIC score": 110.03935871130993}, {"Number of components": 4, "Type of covariance": "diag", "BIC score": 119.54434750427274}, {"Number of components": 5, "Type of covariance": "diag", "BIC score": 130.68355710124123}, {"Number of components": 6, "Type of covariance": "diag", "BIC score": 148.58868630865976}, {"Number of components": 7, "Type of covariance": "diag", "BIC score": 152.281129582613}, {"Number of components": 8, "Type of covariance": "diag", "BIC score": 171.79445789037362}, {"Number of components": 9, "Type of covariance": "diag", "BIC score": 195.5462803005014}, {"Number of components": 10, "Type of covariance": "diag", "BIC score": 209.4318149043126}], "n_cdrs": 149}