{"grid_search": [{"Number of components": 2, "Type of covariance": "diag", "BIC score": 132.5056717119894}, {"Number of components": 1, "Type of covariance": "diag", "BIC score": 134.2695239896705}, {"Number of components": 3, "Type of covariance": "diag", "BIC score": 143.01046825756765}, {"Number of components": 4, "Type of covariance": "diag", "BIC score": 155.80305822718378}, {"Number of components": 5, "Type of covariance": "diag", "BIC score": 178.9791974026149}, {"Number of components": 6, "Type of covariance": "diag", "BIC score": 192.3344553453196}, {"Number of components": 7, "Type of covariance": "diag", "BIC score": 205.08359418557697}, {"Number of components": 8, "Type of covariance": "diag", "BIC score": 219.52422119033562}, {"Number of components": 9, "Type of covariance": "diag", "BIC score": 235.24949399500764}, {"Number of components": 10, "Type of covariance": "diag", "BIC score": 245.016629785568}], "n_cdrs": 214}