{"grid_search": [{"Number of components": 1, "Type of covariance": "diag", "BIC score": 106.96340854495534}, {"Number of components": 2, "Type of covariance": "diag", "BIC score": 120.24126493280376}, {"Number of components": 3, "Type of covariance": "diag", "BIC score": 133.40044345653905}, {"Number of components": 4, "Type of covariance": "diag", "BIC score": 145.95229648372347}, {"Number of components": 5, "Type of covariance": "diag", "BIC score": 157.28400503321134}, {"Number of components": 6, "Type of covariance": "diag", "BIC score": 168.5939733597059}, {"Number of components": 7, "Type of covariance": "diag", "BIC score": 188.51806332093295}, {"Number of components": 8, "Type of covariance": "diag", "BIC score": 194.17073721600426}, {"Number of components": 9, "Type of covariance": "diag", "BIC score": 215.88845420061608}, {"Number of components": 10, "Type of covariance": "diag", "BIC score": 224.85789308330226}], "n_cdrs": 170}