{"grid_search": [{"Number of components": 2, "Type of covariance": "diag", "BIC score": 241.04406778303297}, {"Number of components": 1, "Type of covariance": "diag", "BIC score": 247.95700085893804}, {"Number of components": 3, "Type of covariance": "diag", "BIC score": 264.50608627594727}, {"Number of components": 4, "Type of covariance": "diag", "BIC score": 276.8168758787818}, {"Number of components": 5, "Type of covariance": "diag", "BIC score": 289.7326618351901}, {"Number of components": 6, "Type of covariance": "diag", "BIC score": 331.7548101080002}, {"Number of components": 8, "Type of covariance": "diag", "BIC score": 354.98832811991815}, {"Number of components": 7, "Type of covariance": "diag", "BIC score": 364.15841741086786}, {"Number of components": 9, "Type of covariance": "diag", "BIC score": 401.2282514810254}, {"Number of components": 10, "Type of covariance": "diag", "BIC score": 417.0877907080423}], "n_cdrs": 407}