{"grid_search": [{"Number of components": 1, "Type of covariance": "diag", "BIC score": 212.97862976936887}, {"Number of components": 2, "Type of covariance": "diag", "BIC score": 220.4806209919635}, {"Number of components": 3, "Type of covariance": "diag", "BIC score": 239.155297684881}, {"Number of components": 4, "Type of covariance": "diag", "BIC score": 254.93438804060233}, {"Number of components": 5, "Type of covariance": "diag", "BIC score": 272.76590997886154}, {"Number of components": 6, "Type of covariance": "diag", "BIC score": 283.10356178749277}, {"Number of components": 7, "Type of covariance": "diag", "BIC score": 297.65975644563184}, {"Number of components": 8, "Type of covariance": "diag", "BIC score": 311.54152953151583}, {"Number of components": 9, "Type of covariance": "diag", "BIC score": 324.9105391261276}, {"Number of components": 10, "Type of covariance": "diag", "BIC score": 336.0663766821117}], "n_cdrs": 350}