{"grid_search": [{"Number of components": 1, "Type of covariance": "diag", "BIC score": 76.30124998285604}, {"Number of components": 2, "Type of covariance": "diag", "BIC score": 86.98734194463306}, {"Number of components": 3, "Type of covariance": "diag", "BIC score": 91.91116643627026}, {"Number of components": 4, "Type of covariance": "diag", "BIC score": 111.93782170524926}, {"Number of components": 5, "Type of covariance": "diag", "BIC score": 131.34213254199057}, {"Number of components": 6, "Type of covariance": "diag", "BIC score": 153.3061022895356}, {"Number of components": 7, "Type of covariance": "diag", "BIC score": 161.92427374464597}, {"Number of components": 8, "Type of covariance": "diag", "BIC score": 202.16435537536773}, {"Number of components": 10, "Type of covariance": "diag", "BIC score": 224.36028306581238}, {"Number of components": 9, "Type of covariance": "diag", "BIC score": 248.40422411596836}], "n_cdrs": 115}