{"grid_search": [{"Number of components": 1, "Type of covariance": "diag", "BIC score": 7.1083854116641705}, {"Number of components": 2, "Type of covariance": "diag", "BIC score": 20.0642381575207}, {"Number of components": 3, "Type of covariance": "diag", "BIC score": 1319.2235766736333}, {"Number of components": 4, "Type of covariance": "diag", "BIC score": 4808.654083604824}, {"Number of components": 5, "Type of covariance": "diag", "BIC score": 443422.0399805113}, {"Number of components": 6, "Type of covariance": "diag", "BIC score": NaN}, {"Number of components": 7, "Type of covariance": "diag", "BIC score": NaN}, {"Number of components": 8, "Type of covariance": "diag", "BIC score": NaN}, {"Number of components": 9, "Type of covariance": "diag", "BIC score": NaN}, {"Number of components": 10, "Type of covariance": "diag", "BIC score": NaN}], "n_cdrs": 7}