{"grid_search": [{"Number of components": 5, "Type of covariance": "diag", "BIC score": 3595.0590736636777}, {"Number of components": 6, "Type of covariance": "diag", "BIC score": 3596.128113571069}, {"Number of components": 4, "Type of covariance": "diag", "BIC score": 3601.103394170389}, {"Number of components": 3, "Type of covariance": "diag", "BIC score": 3608.282679832515}, {"Number of components": 7, "Type of covariance": "diag", "BIC score": 3618.4148659053926}, {"Number of components": 8, "Type of covariance": "diag", "BIC score": 3623.9957392060833}, {"Number of components": 9, "Type of covariance": "diag", "BIC score": 3648.0765485416937}, {"Number of components": 10, "Type of covariance": "diag", "BIC score": 3679.2652083341186}, {"Number of components": 2, "Type of covariance": "diag", "BIC score": 3836.316011834231}, {"Number of components": 1, "Type of covariance": "diag", "BIC score": 3921.2579507360597}], "n_cdrs": 6773}