{"grid_search": [{"Number of components": 3, "Type of covariance": "diag", "BIC score": 1916.0997155942866}, {"Number of components": 4, "Type of covariance": "diag", "BIC score": 1918.4751904920097}, {"Number of components": 5, "Type of covariance": "diag", "BIC score": 1934.193192941207}, {"Number of components": 6, "Type of covariance": "diag", "BIC score": 1950.6003682207509}, {"Number of components": 1, "Type of covariance": "diag", "BIC score": 1961.0865396865634}, {"Number of components": 2, "Type of covariance": "diag", "BIC score": 1983.7430565229988}, {"Number of components": 7, "Type of covariance": "diag", "BIC score": 1984.3062303977963}, {"Number of components": 8, "Type of covariance": "diag", "BIC score": 1997.9183784199893}, {"Number of components": 9, "Type of covariance": "diag", "BIC score": 2022.6825360282892}, {"Number of components": 10, "Type of covariance": "diag", "BIC score": 2048.2242027021007}], "n_cdrs": 3406}