{"grid_search": [{"Number of components": 1, "Type of covariance": "diag", "BIC score": 24.063000880195155}, {"Number of components": 2, "Type of covariance": "diag", "BIC score": 27.120296976337595}, {"Number of components": 3, "Type of covariance": "diag", "BIC score": 60.16088554330853}, {"Number of components": 4, "Type of covariance": "diag", "BIC score": 80.18892976877645}, {"Number of components": 5, "Type of covariance": "diag", "BIC score": 113.7416480914338}, {"Number of components": 6, "Type of covariance": "diag", "BIC score": 133.53453493733923}, {"Number of components": 7, "Type of covariance": "diag", "BIC score": 218.3997542971712}, {"Number of components": 8, "Type of covariance": "diag", "BIC score": 672.4756892349408}, {"Number of components": 9, "Type of covariance": "diag", "BIC score": 864.0568687827866}, {"Number of components": 10, "Type of covariance": "diag", "BIC score": 5858.05680324525}], "n_cdrs": 27}