{"grid_search": [{"Number of components": 1, "Type of covariance": "diag", "BIC score": 370.616916607088}, {"Number of components": 2, "Type of covariance": "diag", "BIC score": 382.36768643769057}, {"Number of components": 3, "Type of covariance": "diag", "BIC score": 399.6792815464959}, {"Number of components": 4, "Type of covariance": "diag", "BIC score": 412.82548591292846}, {"Number of components": 5, "Type of covariance": "diag", "BIC score": 430.42079885547736}, {"Number of components": 6, "Type of covariance": "diag", "BIC score": 446.2568728475368}, {"Number of components": 7, "Type of covariance": "diag", "BIC score": 458.71539626479364}, {"Number of components": 8, "Type of covariance": "diag", "BIC score": 474.71237632457525}, {"Number of components": 9, "Type of covariance": "diag", "BIC score": 490.2686509260604}, {"Number of components": 10, "Type of covariance": "diag", "BIC score": 503.17566938113276}], "n_cdrs": 629}