{"grid_search": [{"Number of components": 4, "Type of covariance": "diag", "BIC score": 2699.9834855378745}, {"Number of components": 5, "Type of covariance": "diag", "BIC score": 2718.868480387458}, {"Number of components": 6, "Type of covariance": "diag", "BIC score": 2720.5931130789313}, {"Number of components": 7, "Type of covariance": "diag", "BIC score": 2724.8515780625626}, {"Number of components": 8, "Type of covariance": "diag", "BIC score": 2744.1682412691475}, {"Number of components": 3, "Type of covariance": "diag", "BIC score": 2744.7587462049314}, {"Number of components": 9, "Type of covariance": "diag", "BIC score": 2764.8338005611595}, {"Number of components": 10, "Type of covariance": "diag", "BIC score": 2784.2358602943045}, {"Number of components": 2, "Type of covariance": "diag", "BIC score": 2835.0166901905814}, {"Number of components": 1, "Type of covariance": "diag", "BIC score": 2866.130705213922}], "n_cdrs": 4993}