{"grid_search": [{"Number of components": 1, "Type of covariance": "diag", "BIC score": 509.9941388974209}, {"Number of components": 2, "Type of covariance": "diag", "BIC score": 1973.7338213906921}, {"Number of components": 3, "Type of covariance": "diag", "BIC score": 12870.335845190466}, {"Number of components": 4, "Type of covariance": "diag", "BIC score": 1119099.552917669}, {"Number of components": 5, "Type of covariance": "diag", "BIC score": NaN}, {"Number of components": 6, "Type of covariance": "diag", "BIC score": NaN}, {"Number of components": 7, "Type of covariance": "diag", "BIC score": NaN}, {"Number of components": 8, "Type of covariance": "diag", "BIC score": NaN}, {"Number of components": 9, "Type of covariance": "diag", "BIC score": NaN}, {"Number of components": 10, "Type of covariance": "diag", "BIC score": NaN}], "n_cdrs": 6}