{"grid_search": [{"Number of components": 4, "Type of covariance": "diag", "BIC score": 2518.611701059177}, {"Number of components": 5, "Type of covariance": "diag", "BIC score": 2527.4420017382968}, {"Number of components": 3, "Type of covariance": "diag", "BIC score": 2535.43825537371}, {"Number of components": 6, "Type of covariance": "diag", "BIC score": 2539.5226808863945}, {"Number of components": 7, "Type of covariance": "diag", "BIC score": 2563.2302426520414}, {"Number of components": 8, "Type of covariance": "diag", "BIC score": 2578.2419742122866}, {"Number of components": 9, "Type of covariance": "diag", "BIC score": 2600.9434526539894}, {"Number of components": 1, "Type of covariance": "diag", "BIC score": 2618.011110642941}, {"Number of components": 10, "Type of covariance": "diag", "BIC score": 2619.4997048953037}, {"Number of components": 2, "Type of covariance": "diag", "BIC score": 2623.088351408277}], "n_cdrs": 4562}