{"grid_search": [{"Number of components": 1, "Type of covariance": "diag", "BIC score": 1486.0727796331234}, {"Number of components": 2, "Type of covariance": "diag", "BIC score": 1492.5296704238763}, {"Number of components": 3, "Type of covariance": "diag", "BIC score": 1504.7243532809455}, {"Number of components": 4, "Type of covariance": "diag", "BIC score": 1521.6380749017546}, {"Number of components": 5, "Type of covariance": "diag", "BIC score": 1540.2973426604763}, {"Number of components": 6, "Type of covariance": "diag", "BIC score": 1554.309740629425}, {"Number of components": 7, "Type of covariance": "diag", "BIC score": 1571.046835478539}, {"Number of components": 8, "Type of covariance": "diag", "BIC score": 1588.7043064883553}, {"Number of components": 9, "Type of covariance": "diag", "BIC score": 1607.8308986429172}, {"Number of components": 10, "Type of covariance": "diag", "BIC score": 1627.5215238470146}], "n_cdrs": 2557}