{"grid_search": [{"Number of components": 1, "Type of covariance": "diag", "BIC score": 457.56099937727885}, {"Number of components": 2, "Type of covariance": "diag", "BIC score": 464.2469173546477}, {"Number of components": 3, "Type of covariance": "diag", "BIC score": 470.7101613925694}, {"Number of components": 4, "Type of covariance": "diag", "BIC score": 484.70999185975415}, {"Number of components": 5, "Type of covariance": "diag", "BIC score": 499.67843044366236}, {"Number of components": 6, "Type of covariance": "diag", "BIC score": 516.1235970551612}, {"Number of components": 7, "Type of covariance": "diag", "BIC score": 531.2985279451108}, {"Number of components": 8, "Type of covariance": "diag", "BIC score": 547.590469976406}, {"Number of components": 9, "Type of covariance": "diag", "BIC score": 563.5877159957142}, {"Number of components": 10, "Type of covariance": "diag", "BIC score": 579.3686956707676}], "n_cdrs": 778}