{"grid_search": [{"Number of components": 2, "Type of covariance": "diag", "BIC score": 23450.00543035265}, {"Number of components": 4, "Type of covariance": "diag", "BIC score": 23476.397465737282}, {"Number of components": 3, "Type of covariance": "diag", "BIC score": 23489.803631926676}, {"Number of components": 5, "Type of covariance": "diag", "BIC score": 23528.866447692788}, {"Number of components": 6, "Type of covariance": "diag", "BIC score": 23566.057881522334}, {"Number of components": 7, "Type of covariance": "diag", "BIC score": 23596.186703748303}, {"Number of components": 9, "Type of covariance": "diag", "BIC score": 23627.683739898843}, {"Number of components": 8, "Type of covariance": "diag", "BIC score": 23628.30494395097}, {"Number of components": 10, "Type of covariance": "diag", "BIC score": 23650.633812589902}, {"Number of components": 1, "Type of covariance": "diag", "BIC score": 24580.058398758138}], "n_cdrs": 15151}