{"grid_search": [{"Number of components": 1, "Type of covariance": "diag", "BIC score": 63.023188407254246}, {"Number of components": 2, "Type of covariance": "diag", "BIC score": 74.69842269806531}, {"Number of components": 3, "Type of covariance": "diag", "BIC score": 84.97538681794029}, {"Number of components": 4, "Type of covariance": "diag", "BIC score": 93.20243993735016}, {"Number of components": 5, "Type of covariance": "diag", "BIC score": 127.61762445780975}, {"Number of components": 6, "Type of covariance": "diag", "BIC score": 137.4009424615914}, {"Number of components": 7, "Type of covariance": "diag", "BIC score": 197.26735955194675}, {"Number of components": 9, "Type of covariance": "diag", "BIC score": 292.47323986150906}, {"Number of components": 8, "Type of covariance": "diag", "BIC score": 296.10430858041246}, {"Number of components": 10, "Type of covariance": "diag", "BIC score": 302.78437483948863}], "n_cdrs": 97}