{"grid_search": [{"Number of components": 2, "Type of covariance": "diag", "BIC score": 439.2189477257828}, {"Number of components": 3, "Type of covariance": "diag", "BIC score": 445.21956961317}, {"Number of components": 4, "Type of covariance": "diag", "BIC score": 457.31134620468856}, {"Number of components": 5, "Type of covariance": "diag", "BIC score": 471.8105233759569}, {"Number of components": 1, "Type of covariance": "diag", "BIC score": 474.6471806449796}, {"Number of components": 6, "Type of covariance": "diag", "BIC score": 486.12862733713143}, {"Number of components": 7, "Type of covariance": "diag", "BIC score": 500.9322982038414}, {"Number of components": 8, "Type of covariance": "diag", "BIC score": 516.6337291141986}, {"Number of components": 9, "Type of covariance": "diag", "BIC score": 533.127048393194}, {"Number of components": 10, "Type of covariance": "diag", "BIC score": 549.4371279626096}], "n_cdrs": 795}