{"grid_search": [{"Number of components": 2, "Type of covariance": "diag", "BIC score": 583.3097153629938}, {"Number of components": 3, "Type of covariance": "diag", "BIC score": 591.1046050840083}, {"Number of components": 4, "Type of covariance": "diag", "BIC score": 603.8283895647086}, {"Number of components": 1, "Type of covariance": "diag", "BIC score": 606.0282304339647}, {"Number of components": 5, "Type of covariance": "diag", "BIC score": 618.7615112720202}, {"Number of components": 6, "Type of covariance": "diag", "BIC score": 636.4503551646676}, {"Number of components": 7, "Type of covariance": "diag", "BIC score": 654.7188512605293}, {"Number of components": 8, "Type of covariance": "diag", "BIC score": 671.8539552446762}, {"Number of components": 9, "Type of covariance": "diag", "BIC score": 684.5787450103877}, {"Number of components": 10, "Type of covariance": "diag", "BIC score": 711.408369880492}], "n_cdrs": 1042}