{"grid_search": [{"Number of components": 1, "Type of covariance": "diag", "BIC score": 22.811638594003476}, {"Number of components": 2, "Type of covariance": "diag", "BIC score": 32.79550611782314}, {"Number of components": 3, "Type of covariance": "diag", "BIC score": 47.25764372726233}, {"Number of components": 4, "Type of covariance": "diag", "BIC score": 70.94006504727352}, {"Number of components": 5, "Type of covariance": "diag", "BIC score": 117.66761898874161}, {"Number of components": 6, "Type of covariance": "diag", "BIC score": 144.27930088078793}, {"Number of components": 7, "Type of covariance": "diag", "BIC score": 285.24404622273585}, {"Number of components": 9, "Type of covariance": "diag", "BIC score": 339.441542180038}, {"Number of components": 8, "Type of covariance": "diag", "BIC score": 411.57880351461}, {"Number of components": 10, "Type of covariance": "diag", "BIC score": 542.3062973297352}], "n_cdrs": 28}