{"grid_search": [{"Number of components": 2, "Type of covariance": "diag", "BIC score": 201.17094562006247}, {"Number of components": 1, "Type of covariance": "diag", "BIC score": 201.18135896606265}, {"Number of components": 3, "Type of covariance": "diag", "BIC score": 208.35527178534227}, {"Number of components": 4, "Type of covariance": "diag", "BIC score": 219.00278601809822}, {"Number of components": 5, "Type of covariance": "diag", "BIC score": 233.54901757767726}, {"Number of components": 6, "Type of covariance": "diag", "BIC score": 251.3864692929697}, {"Number of components": 7, "Type of covariance": "diag", "BIC score": 260.4939245086392}, {"Number of components": 8, "Type of covariance": "diag", "BIC score": 277.652060518028}, {"Number of components": 9, "Type of covariance": "diag", "BIC score": 305.109921990265}, {"Number of components": 10, "Type of covariance": "diag", "BIC score": 319.64914989391156}], "n_cdrs": 333}