{"grid_search": [{"Number of components": 2, "Type of covariance": "diag", "BIC score": 172.3668770071416}, {"Number of components": 3, "Type of covariance": "diag", "BIC score": 180.94135133814962}, {"Number of components": 1, "Type of covariance": "diag", "BIC score": 183.81036980223462}, {"Number of components": 4, "Type of covariance": "diag", "BIC score": 192.72977088693526}, {"Number of components": 5, "Type of covariance": "diag", "BIC score": 210.70358528117654}, {"Number of components": 6, "Type of covariance": "diag", "BIC score": 217.77598057440417}, {"Number of components": 7, "Type of covariance": "diag", "BIC score": 238.3292836002567}, {"Number of components": 8, "Type of covariance": "diag", "BIC score": 259.58341937471477}, {"Number of components": 9, "Type of covariance": "diag", "BIC score": 267.71759967895537}, {"Number of components": 10, "Type of covariance": "diag", "BIC score": 288.5142656133338}], "n_cdrs": 306}