{"grid_search": [{"Number of components": 2, "Type of covariance": "diag", "BIC score": 235.81331359779216}, {"Number of components": 1, "Type of covariance": "diag", "BIC score": 245.58777546006826}, {"Number of components": 3, "Type of covariance": "diag", "BIC score": 248.29204107590175}, {"Number of components": 4, "Type of covariance": "diag", "BIC score": 272.7746729715469}, {"Number of components": 5, "Type of covariance": "diag", "BIC score": 292.8546012145203}, {"Number of components": 6, "Type of covariance": "diag", "BIC score": 313.53993372767087}, {"Number of components": 7, "Type of covariance": "diag", "BIC score": 351.62250158972194}, {"Number of components": 8, "Type of covariance": "diag", "BIC score": 370.6299752803906}, {"Number of components": 9, "Type of covariance": "diag", "BIC score": 390.30029324603765}, {"Number of components": 10, "Type of covariance": "diag", "BIC score": 420.1394686971472}], "n_cdrs": 410}