{"grid_search": [{"Number of components": 1, "Type of covariance": "diag", "BIC score": 71.22953265367244}, {"Number of components": 2, "Type of covariance": "diag", "BIC score": 72.18303993390842}, {"Number of components": 3, "Type of covariance": "diag", "BIC score": 75.42123279694381}, {"Number of components": 4, "Type of covariance": "diag", "BIC score": 86.53175840145789}, {"Number of components": 5, "Type of covariance": "diag", "BIC score": 203.9028083310021}, {"Number of components": 6, "Type of covariance": "diag", "BIC score": 218.89379224876566}, {"Number of components": 7, "Type of covariance": "diag", "BIC score": 335.8854444735527}, {"Number of components": 8, "Type of covariance": "diag", "BIC score": 369.84722530023953}, {"Number of components": 10, "Type of covariance": "diag", "BIC score": 652.9834401104101}, {"Number of components": 9, "Type of covariance": "diag", "BIC score": 838.7110468741188}], "n_cdrs": 96}