{"grid_search": [{"Number of components": 4, "Type of covariance": "diag", "BIC score": 3106.925467142307}, {"Number of components": 5, "Type of covariance": "diag", "BIC score": 3135.4944824482627}, {"Number of components": 6, "Type of covariance": "diag", "BIC score": 3162.3643310878224}, {"Number of components": 3, "Type of covariance": "diag", "BIC score": 3181.6732747345604}, {"Number of components": 7, "Type of covariance": "diag", "BIC score": 3183.5377326152293}, {"Number of components": 9, "Type of covariance": "diag", "BIC score": 3230.6046393376782}, {"Number of components": 10, "Type of covariance": "diag", "BIC score": 3243.6601284659673}, {"Number of components": 8, "Type of covariance": "diag", "BIC score": 3263.5206342099345}, {"Number of components": 2, "Type of covariance": "diag", "BIC score": 3882.1326222553334}, {"Number of components": 1, "Type of covariance": "diag", "BIC score": 4292.115530453362}], "n_cdrs": 7325}