{"grid_search": [{"Number of components": 1, "Type of covariance": "diag", "BIC score": 110.0517188874586}, {"Number of components": 2, "Type of covariance": "diag", "BIC score": 133.3525843888172}, {"Number of components": 3, "Type of covariance": "diag", "BIC score": 144.34976266368548}, {"Number of components": 4, "Type of covariance": "diag", "BIC score": 158.83754803883576}, {"Number of components": 5, "Type of covariance": "diag", "BIC score": 167.11786413440063}, {"Number of components": 6, "Type of covariance": "diag", "BIC score": 168.22395351158872}, {"Number of components": 7, "Type of covariance": "diag", "BIC score": 199.47974309459678}, {"Number of components": 8, "Type of covariance": "diag", "BIC score": 209.66037525801198}, {"Number of components": 9, "Type of covariance": "diag", "BIC score": 235.74453627906195}, {"Number of components": 10, "Type of covariance": "diag", "BIC score": 249.05869772525176}], "n_cdrs": 164}