{"grid_search": [{"Number of components": 1, "Type of covariance": "diag", "BIC score": 57.82566024191154}, {"Number of components": 2, "Type of covariance": "diag", "BIC score": 65.50016240747978}, {"Number of components": 3, "Type of covariance": "diag", "BIC score": 76.43967719597997}, {"Number of components": 4, "Type of covariance": "diag", "BIC score": 85.33883679046514}, {"Number of components": 5, "Type of covariance": "diag", "BIC score": 98.9353487731306}, {"Number of components": 6, "Type of covariance": "diag", "BIC score": 109.51612132500789}, {"Number of components": 7, "Type of covariance": "diag", "BIC score": 117.72984092504078}, {"Number of components": 8, "Type of covariance": "diag", "BIC score": 154.34120222874807}, {"Number of components": 9, "Type of covariance": "diag", "BIC score": 162.8343194923355}, {"Number of components": 10, "Type of covariance": "diag", "BIC score": 190.06414255793862}], "n_cdrs": 89}