{"grid_search": [{"Number of components": 3, "Type of covariance": "diag", "BIC score": 1212.7966337781902}, {"Number of components": 2, "Type of covariance": "diag", "BIC score": 1213.037160549188}, {"Number of components": 4, "Type of covariance": "diag", "BIC score": 1217.4543671792126}, {"Number of components": 5, "Type of covariance": "diag", "BIC score": 1223.4221235777677}, {"Number of components": 6, "Type of covariance": "diag", "BIC score": 1238.4223092625016}, {"Number of components": 7, "Type of covariance": "diag", "BIC score": 1252.09887458671}, {"Number of components": 8, "Type of covariance": "diag", "BIC score": 1266.9696988019264}, {"Number of components": 9, "Type of covariance": "diag", "BIC score": 1281.6221411294657}, {"Number of components": 10, "Type of covariance": "diag", "BIC score": 1302.1273132877554}, {"Number of components": 1, "Type of covariance": "diag", "BIC score": 1325.7164419129906}], "n_cdrs": 2276}