{"grid_search": [{"Number of components": 1, "Type of covariance": "diag", "BIC score": 58.979888288659616}, {"Number of components": 2, "Type of covariance": "diag", "BIC score": 64.09397539561567}, {"Number of components": 3, "Type of covariance": "diag", "BIC score": 67.14510752787892}, {"Number of components": 4, "Type of covariance": "diag", "BIC score": 77.84634190174606}, {"Number of components": 5, "Type of covariance": "diag", "BIC score": 111.3889422895035}, {"Number of components": 6, "Type of covariance": "diag", "BIC score": 117.9357150858275}, {"Number of components": 7, "Type of covariance": "diag", "BIC score": 141.76191957944081}, {"Number of components": 8, "Type of covariance": "diag", "BIC score": 144.69322460798145}, {"Number of components": 9, "Type of covariance": "diag", "BIC score": 177.62912876842105}, {"Number of components": 10, "Type of covariance": "diag", "BIC score": 229.33529463291967}], "n_cdrs": 86}