{"grid_search": [{"Number of components": 1, "Type of covariance": "diag", "BIC score": 31.675984820088264}, {"Number of components": 2, "Type of covariance": "diag", "BIC score": 96.64680954252535}, {"Number of components": 3, "Type of covariance": "diag", "BIC score": 209.15330219055278}, {"Number of components": 4, "Type of covariance": "diag", "BIC score": 227.22642467086825}, {"Number of components": 5, "Type of covariance": "diag", "BIC score": 782.0394463962787}, {"Number of components": 6, "Type of covariance": "diag", "BIC score": 961.0843278989408}, {"Number of components": 7, "Type of covariance": "diag", "BIC score": 4396.297949292849}, {"Number of components": 9, "Type of covariance": "diag", "BIC score": 4787.325726063441}, {"Number of components": 8, "Type of covariance": "diag", "BIC score": 4982.928760928154}, {"Number of components": 10, "Type of covariance": "diag", "BIC score": 4990.628250674023}], "n_cdrs": 43}