{"grid_search": [{"Number of components": 3, "Type of covariance": "diag", "BIC score": 713.1016940052646}, {"Number of components": 4, "Type of covariance": "diag", "BIC score": 728.3435399103109}, {"Number of components": 1, "Type of covariance": "diag", "BIC score": 737.0883520494492}, {"Number of components": 5, "Type of covariance": "diag", "BIC score": 737.2744428201206}, {"Number of components": 6, "Type of covariance": "diag", "BIC score": 743.2072917955287}, {"Number of components": 2, "Type of covariance": "diag", "BIC score": 751.595006598156}, {"Number of components": 7, "Type of covariance": "diag", "BIC score": 762.9740683421154}, {"Number of components": 8, "Type of covariance": "diag", "BIC score": 788.1047580232045}, {"Number of components": 9, "Type of covariance": "diag", "BIC score": 798.4962053261037}, {"Number of components": 10, "Type of covariance": "diag", "BIC score": 819.0308917116103}], "n_cdrs": 1270}