{"grid_search": [{"Number of components": 1, "Type of covariance": "diag", "BIC score": 48.75069352179086}, {"Number of components": 3, "Type of covariance": "diag", "BIC score": 53.67232496395313}, {"Number of components": 2, "Type of covariance": "diag", "BIC score": 71.17357267498912}, {"Number of components": 5, "Type of covariance": "diag", "BIC score": 106.73877855534514}, {"Number of components": 6, "Type of covariance": "diag", "BIC score": 155.59976788971477}, {"Number of components": 4, "Type of covariance": "diag", "BIC score": 258.6374527780819}, {"Number of components": 7, "Type of covariance": "diag", "BIC score": 355.6238477688568}, {"Number of components": 8, "Type of covariance": "diag", "BIC score": 1246.4624438406747}, {"Number of components": 9, "Type of covariance": "diag", "BIC score": 2983.1241307969776}, {"Number of components": 10, "Type of covariance": "diag", "BIC score": 8366.391347137269}], "n_cdrs": 65}