{"grid_search": [{"Number of components": 3, "Type of covariance": "diag", "BIC score": 5650.599415712384}, {"Number of components": 4, "Type of covariance": "diag", "BIC score": 5677.0992253095565}, {"Number of components": 5, "Type of covariance": "diag", "BIC score": 5693.015563695055}, {"Number of components": 7, "Type of covariance": "diag", "BIC score": 5721.229419098915}, {"Number of components": 6, "Type of covariance": "diag", "BIC score": 5724.8291845345275}, {"Number of components": 8, "Type of covariance": "diag", "BIC score": 5738.756983422164}, {"Number of components": 9, "Type of covariance": "diag", "BIC score": 5776.838581017165}, {"Number of components": 10, "Type of covariance": "diag", "BIC score": 5799.722814159371}, {"Number of components": 2, "Type of covariance": "diag", "BIC score": 6024.026347697247}, {"Number of components": 1, "Type of covariance": "diag", "BIC score": 8319.980480132865}], "n_cdrs": 14568}