{"grid_search": [{"Number of components": 7, "Type of covariance": "diag", "BIC score": 2675.1996766181464}, {"Number of components": 8, "Type of covariance": "diag", "BIC score": 2701.981632254253}, {"Number of components": 2, "Type of covariance": "diag", "BIC score": 2710.281153939529}, {"Number of components": 5, "Type of covariance": "diag", "BIC score": 2723.56484311389}, {"Number of components": 9, "Type of covariance": "diag", "BIC score": 2724.9502763192995}, {"Number of components": 1, "Type of covariance": "diag", "BIC score": 2744.160192237458}, {"Number of components": 10, "Type of covariance": "diag", "BIC score": 2744.2624818084028}, {"Number of components": 6, "Type of covariance": "diag", "BIC score": 2745.7010096975146}, {"Number of components": 4, "Type of covariance": "diag", "BIC score": 2780.403768474224}, {"Number of components": 3, "Type of covariance": "diag", "BIC score": 2809.169705094082}], "n_cdrs": 4770}