{"grid_search": [{"Number of components": 2, "Type of covariance": "diag", "BIC score": 1202.169602665234}, {"Number of components": 3, "Type of covariance": "diag", "BIC score": 1210.224898482243}, {"Number of components": 4, "Type of covariance": "diag", "BIC score": 1232.6688201154739}, {"Number of components": 5, "Type of covariance": "diag", "BIC score": 1251.921698478836}, {"Number of components": 6, "Type of covariance": "diag", "BIC score": 1267.1459081946089}, {"Number of components": 1, "Type of covariance": "diag", "BIC score": 1280.8423201557846}, {"Number of components": 7, "Type of covariance": "diag", "BIC score": 1289.1031089624391}, {"Number of components": 8, "Type of covariance": "diag", "BIC score": 1308.257992794254}, {"Number of components": 9, "Type of covariance": "diag", "BIC score": 1325.3315620929338}, {"Number of components": 10, "Type of covariance": "diag", "BIC score": 1345.9949846849036}], "n_cdrs": 2208}