{"grid_search": [{"Number of components": 2, "Type of covariance": "diag", "BIC score": 459.55163185907224}, {"Number of components": 1, "Type of covariance": "diag", "BIC score": 460.90047213673427}, {"Number of components": 3, "Type of covariance": "diag", "BIC score": 472.5338747392169}, {"Number of components": 4, "Type of covariance": "diag", "BIC score": 493.5297984028599}, {"Number of components": 5, "Type of covariance": "diag", "BIC score": 511.4235975679352}, {"Number of components": 6, "Type of covariance": "diag", "BIC score": 535.6717096389735}, {"Number of components": 7, "Type of covariance": "diag", "BIC score": 550.110013369768}, {"Number of components": 8, "Type of covariance": "diag", "BIC score": 570.3987030926189}, {"Number of components": 9, "Type of covariance": "diag", "BIC score": 588.5828067744527}, {"Number of components": 10, "Type of covariance": "diag", "BIC score": 608.5701897922249}], "n_cdrs": 778}