{"grid_search": [{"Number of components": 3, "Type of covariance": "diag", "BIC score": 140.1887403486332}, {"Number of components": 4, "Type of covariance": "diag", "BIC score": 151.46460512972857}, {"Number of components": 1, "Type of covariance": "diag", "BIC score": 154.39880891791302}, {"Number of components": 2, "Type of covariance": "diag", "BIC score": 158.26954444591044}, {"Number of components": 5, "Type of covariance": "diag", "BIC score": 164.11740671326612}, {"Number of components": 6, "Type of covariance": "diag", "BIC score": 177.37905953472395}, {"Number of components": 7, "Type of covariance": "diag", "BIC score": 191.17402938814007}, {"Number of components": 8, "Type of covariance": "diag", "BIC score": 214.3417786882325}, {"Number of components": 9, "Type of covariance": "diag", "BIC score": 234.0776606657624}, {"Number of components": 10, "Type of covariance": "diag", "BIC score": 250.91597697272272}], "n_cdrs": 247}