{"grid_search": [{"Number of components": 1, "Type of covariance": "diag", "BIC score": 399.0045225711127}, {"Number of components": 2, "Type of covariance": "diag", "BIC score": 409.7861185966981}, {"Number of components": 3, "Type of covariance": "diag", "BIC score": 431.638809120559}, {"Number of components": 4, "Type of covariance": "diag", "BIC score": 439.7139211589776}, {"Number of components": 5, "Type of covariance": "diag", "BIC score": 449.6172485668566}, {"Number of components": 6, "Type of covariance": "diag", "BIC score": 453.2200590390539}, {"Number of components": 7, "Type of covariance": "diag", "BIC score": 471.0475503162312}, {"Number of components": 8, "Type of covariance": "diag", "BIC score": 486.168864020633}, {"Number of components": 9, "Type of covariance": "diag", "BIC score": 501.5895429636139}, {"Number of components": 10, "Type of covariance": "diag", "BIC score": 514.4762945663472}], "n_cdrs": 671}